tgbotapi/__init__.py
tgbotapi/__version__.py
tgbotapi/asyncbot.py
tgbotapi/bot.py
tgbotapi/methods.py
tgbotapi/types.py
tgbotapi/utils/__init__.py
tgbotapi/utils/api_exceptions.py
tgbotapi/utils/api_handler.py
tgbotapi/utils/api_worker.py
tgbotapi/utils/json_helper.py
tgbotapi/utils/logger.py
tgbotapi-6.0.0.dist-info/LICENSE
tgbotapi-6.0.0.dist-info/METADATA
tgbotapi-6.0.0.dist-info/WHEEL
tgbotapi-6.0.0.dist-info/top_level.txt
tgbotapi-6.0.0.dist-info/RECORD
