Metadata-Version: 2.1
Name: tgbotapi
Version: 6.0.0
Summary: Telegram Bot API Framework
Home-page: https://github.com/MA24th/tgbotapi
Author: Mustafa Asaad
Author-email: ma24th@yahoo.com
License: GPLv2
Keywords: telegram-bot-api,tgbotapi,framework,telegram bot api,bot api
Classifier: Topic :: Software Development
Classifier: Development Status :: 5 - Production/Stable
Classifier: License :: OSI Approved :: GNU General Public License v2 (GPLv2)
Classifier: Programming Language :: Python :: 3.6
Classifier: Programming Language :: Python :: 3.7
Classifier: Programming Language :: Python :: 3.8
Classifier: Programming Language :: Python :: 3.9
Classifier: Programming Language :: Python :: 3.10
Classifier: Intended Audience :: Developers
Classifier: Operating System :: OS Independent
Classifier: Natural Language :: English
License-File: LICENSE
Requires-Dist: requests
